[
  {
    "id": "7a57c1de-b899-4e1c-bd0b-ce741407ce7e",
    "course_id": "1a9c9747-23be-4a9b-b961-53e311eaaa02",
    "titulo": "Fundamentos da Producao",
    "descricao": "",
    "ordem": 0,
    "created_at": "2026-06-30T06:41:18.598424+00:00",
    "updated_at": "2026-06-30T06:41:18.598424+00:00",
    "parent_id": null,
    "lessons": [
      {
        "id": "b4747802-ed8c-483f-9378-db4af8d20152",
        "tipo": "texto",
        "ordem": 0,
        "titulo": "O Papel da Produção e o Run of Show",
        "pdf_path": null,
        "tem_quiz": false,
        "descricao": null,
        "module_id": "7a57c1de-b899-4e1c-bd0b-ce741407ce7e",
        "created_at": "2026-06-30T06:41:18.856158+00:00",
        "updated_at": "2026-06-30T06:41:18.856158+00:00",
        "youtube_id": null,
        "duracao_min": 15,
        "conteudo_rico": "<p><strong>O que faz a produção.</strong> O produtor é quem organiza o evento do começo ao fim: contrata e coordena a equipe técnica (som, luz, vídeo, estrutura), controla o tempo, fala com o cliente e resolve imprevistos. Sem produção, cada área puxa para um lado.</p><p><strong>O Run of Show (linha do tempo do evento).</strong> É o documento que diz o que acontece, a que horas e quem é responsável. Ele transforma o dia num passo a passo claro.</p><ul><li><strong>Load-in / Descarga:</strong> chega o caminhão, descarrega o material.</li><li><strong>Montagem de estrutura (rigging):</strong> treliça, palco, pontos de içamento.</li><li><strong>Montagem de som e luz</strong> e depois <strong>energia e testes</strong>.</li><li><strong>Passagem de som (soundcheck):</strong> ajusta tudo antes do público.</li><li><strong>Abertura da casa / portas:</strong> o público entra.</li><li><strong>Show / evento</strong>, <strong>encerramento</strong> e <strong>desmontagem (load-out)</strong>.</li></ul><p><strong>Por que a ordem importa.</strong> Cada fase prepara a próxima: não dá pra passar som antes de montar, nem abrir as portas antes do soundcheck. Pular ou inverter etapas gera atraso e risco.</p><p><strong>Na prática:</strong> no simulador abaixo, monte o dia do evento na ordem certa, do load-in à desmontagem.</p>",
        "preview_gratis": true
      },
      {
        "id": "82a60186-b081-4836-81b4-e45b18fb066b",
        "tipo": "texto",
        "ordem": 1,
        "titulo": "Cliente: Show × Corporativo",
        "pdf_path": null,
        "tem_quiz": false,
        "descricao": null,
        "module_id": "7a57c1de-b899-4e1c-bd0b-ce741407ce7e",
        "created_at": "2026-06-30T06:41:19.566316+00:00",
        "updated_at": "2026-06-30T06:41:19.566316+00:00",
        "youtube_id": null,
        "duracao_min": 15,
        "conteudo_rico": "<p><strong>O mesmo técnico, necessidades diferentes.</strong> A base técnica (cabos, energia, sinal) é igual em qualquer evento. O que muda é a <strong>necessidade do cliente</strong> — e ler isso certo é o que define o orçamento e a montagem.</p><p><strong>Evento de SHOW</strong> (música ao vivo, festa, espetáculo):</p><ul><li>PA potente com subgrave, retornos/monitores de palco;</li><li>Backline (bateria, amplificadores, instrumentos);</li><li>Iluminação cênica (moving heads, cores, efeitos).</li></ul><p><strong>Evento CORPORATIVO</strong> (palestra, convenção, lançamento):</p><ul><li>Fala clara: microfone de lapela/gooseneck, boa inteligibilidade;</li><li>Projeção de slides / telão, apresentação visual;</li><li>Gravação e transmissão (streaming), às vezes tradução simultânea.</li></ul><p><strong>E o que serve para os dois?</strong> Energia segura, microfone sem fio de mão, equipe organizada — a base que todo evento precisa.</p><p><strong>Na prática:</strong> no jogo abaixo, classifique cada necessidade como Show, Corporativo ou Ambos.</p>",
        "preview_gratis": false
      }
    ]
  }
]